azure_kusto_mcp-0.0.14.dist-info/licenses/LICENSE
kusto_mcp/__init__.py
kusto_mcp/_version.py
kusto_mcp/common.py
kusto_mcp/kusto_config.py
kusto_mcp/kusto_connection.py
kusto_mcp/kusto_response_formatter.py
kusto_mcp/kusto_service.py
kusto_mcp/server.py
azure_kusto_mcp-0.0.14.dist-info/METADATA
azure_kusto_mcp-0.0.14.dist-info/WHEEL
azure_kusto_mcp-0.0.14.dist-info/entry_points.txt
azure_kusto_mcp-0.0.14.dist-info/top_level.txt
azure_kusto_mcp-0.0.14.dist-info/RECORD
